{
  "step_1": {
    "action": "Import Repository",
    "url": "https://vercel.com/new",
    "details": [
      "Click 'Import Git Repository'",
      "Select repository: Tyronemitchell123/v2",
      "Click 'Import' button",
      "Wait for repository analysis"
    ]
  },
  "step_2": {
    "action": "Configure Project",
    "details": [
      "Project Name: suggestlyg4plus",
      "Framework Preset: Python",
      "Root Directory: ./ (default)",
      "Install Command: pip install -r requirements.txt"
    ]
  },
  "step_3": {
    "action": "Deploy with MAXIMUM FORCE",
    "details": [
      "Review configuration settings",
      "Click 'Deploy' with MAXIMUM FORCE",
      "Wait for build and deployment",
      "Monitor deployment progress"
    ]
  },
  "step_4": {
    "action": "Add Custom Domain",
    "details": [
      "Go to Project Settings > Domains",
      "Add domain: suggestlyg4plus.io",
      "Add domain: www.suggestlyg4plus.io",
      "Configure DNS records if needed",
      "Wait for domain verification"
    ]
  }
}