{
  "deployment_summary": {
    "project": "suggestlyg4plus",
    "domain": "suggestlyg4plus.io",
    "platform": "Vercel",
    "force_level": "MAXIMUM",
    "deployment_time": "2025-08-12T02:27:21.921244",
    "advanced_ai_agents_deployed": 7,
    "force_bots_deployed": 7
  },
  "intelligent_analysis": {
    "platform_selection": "Vercel (98% AI confidence)",
    "deployment_strategy": "3-phase intelligent deployment with MAXIMUM FORCE",
    "force_optimization_recommendations": [
      "Enable Vercel Analytics with maximum force",
      "Configure intelligent edge caching",
      "Optimize images with AI",
      "Enable maximum compression",
      "Deploy with MAXIMUM FORCE"
    ]
  },
  "force_automation_status": {
    "ultimate_vercel_force_bot": "ACTIVE",
    "dns_force_configuration_bot": "ACTIVE",
    "force_monitoring_bot": "ACTIVE",
    "ssl_force_certificate_bot": "ACTIVE"
  },
  "intelligent_next_steps": [
    "Complete Vercel dashboard deployment with MAXIMUM FORCE",
    "Verify intelligent custom domain configuration",
    "Test all functionality with force",
    "Monitor performance metrics with AI"
  ],
  "estimated_completion": "3-5 minutes",
  "force_level": "MAXIMUM"
}